album_image_util/__init__.py
album_image_util/template_image_data.py
album_image_util/util.py
album_image_util-0.1.0.dist-info/METADATA
album_image_util-0.1.0.dist-info/WHEEL
album_image_util-0.1.0.dist-info/RECORD
