Metadata-Version: 2.1
Name: album-image-util
Version: 0.1.0
Summary: Utility for creating album of the day images
Author: William04A
Author-email: 35110380+William04A@users.noreply.github.com
Requires-Python: >=3.9,<4.0
Classifier: Programming Language :: Python :: 3
Classifier: Programming Language :: Python :: 3.9
Classifier: Programming Language :: Python :: 3.10
Classifier: Programming Language :: Python :: 3.11
Requires-Dist: pillow (>=10.0.0,<11.0.0)
